cycept/__init__.py
cycept/call.py
cycept/compile.py
cycept/core.py
cycept/tests/__init__.py
cycept/tests/test_bench.py
cycept/tests/test_cycept.py
cycept-0.0.6.dist-info/LICENSE
cycept-0.0.6.dist-info/METADATA
cycept-0.0.6.dist-info/WHEEL
cycept-0.0.6.dist-info/top_level.txt
cycept-0.0.6.dist-info/RECORD
