Metadata-Version: 2.1
Name: cycept
Version: 0.0.6
Summary: Effortless just-in-time compilation of Python functions, powered by Cython
Author-email: Jeppe Dakin <jeppe_dakin@hotmail.com>
Project-URL: Download, https://pypi.python.org/pypi/cycept
Project-URL: Changelog, https://github.com/jmd-dk/cycept/blob/main/CHANGELOG.md
Project-URL: Bug Tracker, https://github.com/jmd-dk/cycept/issues
Project-URL: Source code, https://github.com/jmd-dk/cycept
Classifier: Intended Audience :: Developers
Classifier: Intended Audience :: Science/Research
Classifier: License :: OSI Approved :: MIT License
Classifier: Operating System :: OS Independent
Classifier: Programming Language :: Python :: 3
Classifier: Programming Language :: Python :: 3.9
Classifier: Programming Language :: Python :: 3.10
Classifier: Programming Language :: Python :: 3.11
Classifier: Programming Language :: Python :: Implementation :: CPython
Classifier: Programming Language :: C
Classifier: Programming Language :: C++
Classifier: Programming Language :: Cython
Classifier: Topic :: Scientific/Engineering
Classifier: Topic :: Software Development :: Code Generators
Classifier: Topic :: Software Development :: Compilers
Classifier: Topic :: Software Development :: Libraries :: Python Modules
Requires-Python: >=3.9
License-File: LICENSE
Requires-Dist: cython (<3.1,>=3.0.0b1)
Requires-Dist: numpy (<1.25,>=1.21.0)
Requires-Dist: setuptools (<68,>=65.6.0)
Requires-Dist: tomli (<2.1,>=1.1.0) ; python_version < "3.11"
Provides-Extra: bench
Requires-Dist: numba (<0.58) ; extra == 'bench'
Provides-Extra: repl
Requires-Dist: dill (<0.4,>=0.2.0) ; extra == 'repl'
Provides-Extra: test
Requires-Dist: pytest (<7.4,>=7.3.0) ; extra == 'test'
